harzcoin/__init__.py
harzcoin-4.3.0.dist-info/WHEEL
harzcoin-4.3.0.dist-info/METADATA
harzcoin-4.3.0.dist-info/RECORD
