Metadata-Version: 2.4
Name: harzcoin
Version: 4.3.0
Summary: Totally better currency frfr (now it's semi-decentralised!?)
Author-email: hrsiz <harsizstudio@gmail.com>
Requires-Dist: requests
Requires-Dist: flit_core>=3.11,<4
Requires-Dist: pytest ; extra == "dev"
Requires-Dist: black ; extra == "dev"
Requires-Dist: tk ; extra == "gui"
Provides-Extra: dev
Provides-Extra: gui
